youterm/__init__.py
youterm/__main__.py
youterm/colorizer.py
youterm/date.py
youterm/text.py
youterm/yt.py
youterm-0.2.0.dist-info/LICENSE
youterm-0.2.0.dist-info/METADATA
youterm-0.2.0.dist-info/WHEEL
youterm-0.2.0.dist-info/entry_points.txt
youterm-0.2.0.dist-info/top_level.txt
youterm-0.2.0.dist-info/RECORD
